doublesided/__init__.py
doublesided/card.py
doublesided/font.py
doublesided/image.py
doublesided/layout.py
doublesided/paper.py
doublesided-0.0.1.dist-info/METADATA
doublesided-0.0.1.dist-info/WHEEL
doublesided-0.0.1.dist-info/licenses/LICENSE
doublesided-0.0.1.dist-info/RECORD
